{"cameraMode":{"drawMode":0,"name":"Shaded","section":"Shading Mode"},"sceneLighting":true,"audioPlay":false,"sceneViewState":{"m_AlwaysRefresh":false,"showFog":true,"showSkybox":true,"showFlares":true,"showImageEffects":true,"showParticleSystems":true,"showVisualEffectGraphs":true,"m_FxEnabled":true},"in2DMode":false,"pivot":{"x":-0.4921274185180664,"y":-0.93463134765625,"z":0.5340008735656738},"rotation":{"x":-0.1296854019165039,"y":0.7960241436958313,"z":-0.1837068796157837,"w":-0.5619425773620606},"size":7.581742286682129,"orthographic":false}