{"cameraMode":{"drawMode":0,"name":"Shaded","section":"Shading Mode"},"sceneLighting":true,"audioPlay":false,"sceneViewState":{"m_AlwaysRefresh":false,"showFog":true,"showSkybox":true,"showFlares":true,"showImageEffects":true,"showParticleSystems":true,"showVisualEffectGraphs":true,"m_FxEnabled":true},"in2DMode":false,"pivot":{"x":-21.047405242919923,"y":-21.89609146118164,"z":15.830244064331055},"rotation":{"x":0.35435014963150027,"y":-0.2913908064365387,"z":0.11723396182060242,"w":0.8807796835899353},"size":24.821346282958986,"orthographic":false}